odoo/addons/mrp_request_bom_structure/README.rst
odoo/addons/mrp_request_bom_structure/__init__.py
odoo/addons/mrp_request_bom_structure/__manifest__.py
odoo/addons/mrp_request_bom_structure/data/config_parameter.xml
odoo/addons/mrp_request_bom_structure/i18n/fr.po
odoo/addons/mrp_request_bom_structure/i18n/it.po
odoo/addons/mrp_request_bom_structure/i18n/mrp_request_bom_structure.pot
odoo/addons/mrp_request_bom_structure/i18n/pt_BR.po
odoo/addons/mrp_request_bom_structure/models/__init__.py
odoo/addons/mrp_request_bom_structure/models/bom_structure.py
odoo/addons/mrp_request_bom_structure/models/mrp_request.py
odoo/addons/mrp_request_bom_structure/readme/CONTRIBUTORS.rst
odoo/addons/mrp_request_bom_structure/readme/DESCRIPTION.rst
odoo/addons/mrp_request_bom_structure/readme/ROADMAP.rst
odoo/addons/mrp_request_bom_structure/readme/USAGE.rst
odoo/addons/mrp_request_bom_structure/static/description/icon.png
odoo/addons/mrp_request_bom_structure/static/description/index.html
odoo/addons/mrp_request_bom_structure/tests/__init__.py
odoo/addons/mrp_request_bom_structure/tests/test_request_structure.py
odoo/addons/mrp_request_bom_structure/views/mrp_request.xml
odoo12_addon_mrp_request_bom_structure-12.0.1.0.0.99.dev10.dist-info/METADATA
odoo12_addon_mrp_request_bom_structure-12.0.1.0.0.99.dev10.dist-info/WHEEL
odoo12_addon_mrp_request_bom_structure-12.0.1.0.0.99.dev10.dist-info/top_level.txt
odoo12_addon_mrp_request_bom_structure-12.0.1.0.0.99.dev10.dist-info/RECORD
